{
    "HBG49A: Sociologie en samenleving": {
        "nl": {
            "[[ ]ecolo[^ ]+, klima+t[^ ]*, overgang]": [
                " en uitdagingen   1  ecologische risico s wereldwijd",
                "ijd en bij ons  van klimaatrisico s tot corona    2  ",
                "ief  we schetsen de overgang naar een mondiale r",
                "atieprocessen en de overgang naar een superdiver"
            ]
        }
    },
    "HBS14G: Biologie: Plantenfysiologie en ecologie": {
        "nl": {
            "[bio(?:diversiteit|sfeer), [ ]ecolo[^ ]+]": [
                "lieuproblematieken  biodiversiteit en duurzaamheid mos",
                "plantenfysiologie en ecologie inhoud fysiologie e",
                "zetting fotosynthese ecologie relaties tussen org"
            ],
            "[bio(?:diversiteit|sfeer), ecosyst[^ ]+]": [
                "lieuproblematieken  biodiversiteit en duurzaamheid mos",
                "oren  biotoopstudie ecosystemen en kringlopen  inte",
                " en dynamiek in een ecosysteem materie- en energie"
            ],
            "[bio(?:diversiteit|sfeer), proble+m, milieu|[ ]ecolo[^ ]+|ecosyst[^ ]+]": [
                "lieuproblematieken  biodiversiteit en duurzaamheid mos",
                "  reducenten  milieuproblematieken  biodiversit",
                "plantenfysiologie en ecologie inhoud fysiologie e",
                "zetting fotosynthese ecologie relaties tussen org",
                "n en dieren aan het milieu samenhang tussen or",
                "n organismen en het milieu  biotische en abiot",
                "oren  biotoopstudie ecosystemen en kringlopen  inte",
                "n organismen en hun milieu successie   climax ",
                " en dynamiek in een ecosysteem materie- en energie",
                "menten  reducenten  milieuproblematieken  biod",
                "n duurzaamheid mos  milieu op school doelstell"
            ],
            "[[ ]ecolo[^ ]+, duurzaamheid]": [
                "plantenfysiologie en ecologie inhoud fysiologie e",
                "zetting fotosynthese ecologie relaties tussen org",
                "  biodiversiteit en duurzaamheid mos  milieu op scho"
            ],
            "milieuproble+m": [
                "menten  reducenten  milieuproblematieken  biodiversit"
            ],
            "(?:milieu|[ ]ecolo[^ ]+|ecosyst[^ ]+)proble+m": [
                "menten  reducenten  milieuproblematieken  biodiversit"
            ]
        }
    },
    "HBS32F: Aardrijkskunde: Landbouw en voedsel": {
        "nl": {
            "duurzame ontwikkelingsdoel(?:en|stelling)?": [
                "mdoelstellingen  de duurzame ontwikkelingsdoelen  sdg   3 daagse exc"
            ]
        }
    },
    "JPBWB6: Algemene economie": {
        "nl": {
            "[duurzame ontwikkeling, milieu|[ ]ecolo[^ ]+]": [
                "rekkingen milieu en duurzame ontwikkeling overheid doelstelli",
                "ionale betrekkingen milieu en duurzame ontwikk"
            ]
        }
    },
    "JPBWB7: Industri\u00eble processing": {
        "nl": {
            "energie[- ]?balans": [
                "1  massabalansen 2  energiebalansen 3  meng- en schei"
            ]
        }
    },
    "JPBWE1: Plantenbescherming": {
        "nl": {
            "[[ ]ecolo[^ ]+, duurzaamheid]": [
                "ing  duurzaamheid op ecologisch en sociaal vlak kom",
                "plantenbescherming  duurzaamheid op ecologisch en so"
            ],
            "biologische landbouw": [
                "producten dat in de biologische landbouw mag worden toegepas"
            ],
            "duurzame productie": [
                " een hoeksteen voor duurzame productie in land- en tuinbou"
            ]
        }
    },
    "JPBWG5: Energietechnologie": {
        "nl": {
            "energie[- ]?(?:ge|ver)bruik|(?:ge|ver)bruik van energie": [
                "ookgassen rationeel energiegebruik duurzame energiepro"
            ],
            "energie[- ]?transitie": [
                "gie en het klimaat  energietransitie en energie instanti"
            ],
            "windenergie": [
                "dstoffen  zonne- en windenergie de energiemarkt doe"
            ]
        }
    },
    "JPO0T5: TE1-2b Elektriciteit wisselstroom": {
        "nl": {
            "fossiele brandstof": [
                " steg centrales o   fossiele brandstoffen o   kernenergie "
            ]
        }
    },
    "JPO0TK: PAV1-2b Ruimtelijke en maatschappelijke ori\u00ebntatie": {
        "nl": {
            "fossiele brandstof": [
                "eenheid 13  energie fossiele brandstoffen andere energiebr"
            ]
        }
    },
    "JPOW14: STEM3-2 Verdieping": {
        "nl": {
            "[duurzame ontwikkeling, milieu, [ ]ecolo[^ ]+|ecosyst[^ ]+]": [
                "urzaam toerisme     duurzame ontwikkeling  ecologische voetaf",
                "viteit op de natuur milieuproblemen als gevolg",
                "van de aarde  basis milieukunde als begrip in ",
                " de wetenschappen - milieurelevante maatschapp",
                "lstellingen van het milieubeleid - de milieuco",
                "t milieubeleid - de milieucompartimenten  luch",
                "em  indeling van de milieuproblemen mondiale m",
                "uproblemen mondiale milieuproblemen   global c",
                "osfeer continentale milieuproblemen   toename ",
                "uviale en regionale milieuproblemen   vermesti",
                "urzame ontwikkeling  ecologische voetafdruk en draag"
            ],
            "[duurzame ontwikkeling, milieu-?proble+m]": [
                "urzaam toerisme     duurzame ontwikkeling  ecologische voetaf",
                "viteit op de natuur milieuproblemen als gevolg van la",
                "em  indeling van de milieuproblemen mondiale milieupr",
                "uproblemen mondiale milieuproblemen   global climate ",
                "osfeer continentale milieuproblemen   toename van ozo",
                "uviale en regionale milieuproblemen   vermesting van "
            ],
            "[duurzame ontwikkeling, milieu|[ ]ecolo[^ ]+]": [
                "urzaam toerisme     duurzame ontwikkeling  ecologische voetaf",
                "viteit op de natuur milieuproblemen als gevolg",
                "urzame ontwikkeling  ecologische voetafdruk en draag",
                "van de aarde  basis milieukunde als begrip in ",
                " de wetenschappen - milieurelevante maatschapp",
                "lstellingen van het milieubeleid - de milieuco",
                "t milieubeleid - de milieucompartimenten  luch",
                "em  indeling van de milieuproblemen mondiale m",
                "uproblemen mondiale milieuproblemen   global c",
                "osfeer continentale milieuproblemen   toename ",
                "uviale en regionale milieuproblemen   vermesti"
            ],
            "[milieu, vervuiling, duurzame ontwikkeling]": [
                "viteit op de natuur milieuproblemen als gevolg",
                "van de aarde  basis milieukunde als begrip in ",
                " de wetenschappen - milieurelevante maatschapp",
                "lstellingen van het milieubeleid - de milieuco",
                "t milieubeleid - de milieucompartimenten  luch",
                "em  indeling van de milieuproblemen mondiale m",
                "uproblemen mondiale milieuproblemen   global c",
                "osfeer continentale milieuproblemen   toename ",
                "uviale en regionale milieuproblemen   vermesti",
                "water en rivieren   vervuiling door materialen en ",
                "urzaam toerisme     duurzame ontwikkeling  ecologische voetaf"
            ],
            "[vervuiling, rivier]": [
                "water en rivieren   vervuiling door materialen en ",
                "em   grond water en rivieren   vergiftiging va",
                "em   grond water en rivieren   vervuiling door"
            ],
            "duurzame landbouw": [
                "leven in de steden  duurzame landbouw  duurzaam toerisme "
            ],
            "milieubeleid": [
                "lstellingen van het milieubeleid - de milieucomparti"
            ],
            "milieuproble+m": [
                "viteit op de natuur milieuproblemen als gevolg van la",
                "em  indeling van de milieuproblemen mondiale milieupr",
                "uproblemen mondiale milieuproblemen   global climate ",
                "osfeer continentale milieuproblemen   toename van ozo",
                "uviale en regionale milieuproblemen   vermesting van "
            ],
            "(?:milieu|[ ]ecolo[^ ]+|ecosyst[^ ]+)proble+m": [
                "viteit op de natuur milieuproblemen als gevolg van la",
                "em  indeling van de milieuproblemen mondiale milieupr",
                "uproblemen mondiale milieuproblemen   global climate ",
                "osfeer continentale milieuproblemen   toename van ozo",
                "uviale en regionale milieuproblemen   vermesting van "
            ]
        }
    },
    "JPOW40: PAV2-1b Wetenschap en techniek": {
        "nl": {
            "[klima+t[^ ]*, milieu, [ ]ecolo[^ ]+": [
                "ilieuzorg op school klimaatverandering leereenheid 10  nat",
                "heid 9  ecologie en milieu planten dieren ecos",
                " dieren ecosystemen milieuzorg op school klima",
                "elden leereenheid 9  ecologie en milieu planten"
            ],
            "klimaatverandering": [
                "ilieuzorg op school klimaatverandering leereenheid 10  nat"
            ]
        }
    },
    "JPOWC3: EC3-1a Algemene economie 5": {
        "nl": {
            "[duurzame ontwikkeling, milieu|[ ]ecolo[^ ]+]": [
                "r  groei  milieu en duurzame ontwikkeling overheid doelstelli",
                "conjunctuur  groei  milieu en duurzame ontwikk"
            ]
        }
    },
    "JPW00J: 4 Technische uitrusting 1": {
        "nl": {
            "klimaatverandering": [
                "s - algemeen kader  klimaatverandering in een geglobalisee"
            ]
        }
    },
    "JPW03Y: Energietechnologie 2": {
        "nl": {
            "energie[- ]?(?:ge|ver)bruik|(?:ge|ver)bruik van energie": [
                "anzet tot rationeel energiegebruik - energieverbruiken",
                "el energiegebruik - energieverbruiken  theorie + oefeni"
            ]
        }
    },
    "JPW0IN: Ecotoxicologie": {
        "nl": {
            "ecotoxicologie": [
                "ecotoxicologie inhoud situering va"
            ]
        }
    },
    "JPW0JD: Milieubiotechnologie": {
        "nl": {
            "[plastic, pollutie]": [
                "ingsmiddelen 6 3 bioplastics 6 4 transgene plan",
                " 5  remediering van pollutie 5 1 inleiding/biobr",
                "ie 6  preventie van pollutie 6 1 inleiding 6 2 g"
            ]
        }
    },
    "JPW0LS: Milieutechnologie 1: water": {
        "nl": {
            "decarbon[^ ]+": [
                "ssing - ontharding  decarbonatie en demineralisatie "
            ]
        }
    },
    "JPW134: Smart grids & e-mobility": {
        "nl": {
            "hernieuwbare energie": [
                "ntrale productie en hernieuwbare energie  wat is de impact o"
            ]
        }
    },
    "JPW187: Milieu- en Afvalmanagement": {
        "nl": {
            "milieu[- ]?vriendelijk": [
                " een ecologische en milieuvriendelijke  werk omgeving  - "
            ],
            "milieu[- ]?wet": [
                "tstandkoming van de milieuwetenschappen en milieu"
            ],
            "milieuregelgeving": [
                "ieuwetenschappen en milieuregelgeving  mondiale  continen",
                "ale milieuproblemen milieuregelgeving/omgevingswetgeving "
            ],
            "milieuproble+m": [
                " fluviale en lokale milieuproblemen milieuregelgeving"
            ],
            "(?:milieu|[ ]ecolo[^ ]+|ecosyst[^ ]+)proble+m": [
                " fluviale en lokale milieuproblemen milieuregelgeving"
            ]
        }
    },
    "JPW253: Fysica 1B": {
        "nl": {
            "[elektri[^ ]+, opslag]": [
                " elektromagnetisme -elektrische lading en elektrisc",
                "ektrische lading en elektrisch veld -elektrische p",
                "en elektrisch veld -elektrische potentiaal -opslag ",
                "entiaal -opslag van elektrische energie -elektrisch",
                "lektrische energie -elektrische stroom -gelijkstroo",
                "trische potentiaal -opslag van elektrische ene"
            ]
        }
    },
    "JPW258: Fysica 2 - Geluid": {
        "nl": {
            "milieu[- ]?wet": [
                " en geluidsspectra *milieuwetgeving  vlarem en co"
            ]
        }
    },
    "JPW260: Milieutechnologie 3: afval- en materialenbeheer / energiebeheer": {
        "nl": {
            "[recycl[^ ]+, milieu]": [
                "eling  sortering en recyclage van enkele huishoud",
                "milieutechnologie 3  afval",
                "n 2 afvalpreventie  milieuverantwoorde consump"
            ],
            "energie[- ]?(?:ge|ver)bruik|(?:ge|ver)bruik van energie": [
                "ergietechnieken 2 1 energieverbruik 2 2 energieproducti"
            ],
            "energie[- ]?balans": [
                "1 6 energie-audit / energiebalans 2 specifieke energi"
            ]
        }
    },
    "JPW294: Slimme huisinstallaties": {
        "nl": {
            "hernieuwbare energie": [
                "sier energiefactuur hernieuwbare energie pv-installaties ele"
            ]
        }
    },
    "JPW295: Hernieuwbare energie en energieproductie": {
        "nl": {
            "fotovoltaische?[- ]?energie": [
                "jf en netgekoppeld  fotovoltaische energie windturbine/energie"
            ],
            "hernieuwbare energie": [
                "hernieuwbare energie en energieproductie",
                "e inhoud inleiding  hernieuwbare energie - european green de",
                "energiebuffers voor hernieuwbare energie-toepassingen doelst"
            ],
            "windenergie": [
                "d solar power  csp  windenergie  turbines  moderne "
            ],
            "zonne[- ]?energie": [
                " fit for 55 -pakket zonne-energie  fotovoltaische sys"
            ]
        }
    },
    "JPW325: Aandrijvingen en energieomvormers": {
        "nl": {
            "windenergie": [
                "generator  dfig  in windenergietoepassing doelstell"
            ]
        }
    },
    "JPW355: Ecologie - Milieubeheer": {
        "nl": {
            "[bio(?:diversiteit|sfeer), [ ]ecolo[^ ]+]": [
                " componenten van de biosfeer  de natuurlijke cyc",
                "pij uitvoeren op de biosfeer en verschillende ec",
                "en  wat is ecologie biosfeer - hydrosfeer - lith",
                "andinname impact op biodiversiteit doelstellingen http",
                " ecosysteem  het vak ecologie is daarom opgedeeld",
                "illende ecosystemen  ecologisch functioneren  wat i",
                "functioneren  wat is ecologie biosfeer - hydrosfe"
            ],
            "[bio(?:diversiteit|sfeer), ecosyst[^ ]+]": [
                " componenten van de biosfeer  de natuurlijke cyc",
                "pij uitvoeren op de biosfeer en verschillende ec",
                "en  wat is ecologie biosfeer - hydrosfeer - lith",
                "andinname impact op biodiversiteit doelstellingen http",
                "unctioneren van een ecosysteem  het vak ecologie i",
                "er en verschillende ecosystemen  ecologisch functio",
                "ynamiek dynamiek in ecosystemen antropogene invloed"
            ],
            "[bio(?:diversiteit|sfeer), impact, milieu|[ ]ecolo[^ ]+|ecosyst[^ ]+]": [
                " componenten van de biosfeer  de natuurlijke cyc",
                "pij uitvoeren op de biosfeer en verschillende ec",
                "en  wat is ecologie biosfeer - hydrosfeer - lith",
                "andinname impact op biodiversiteit doelstellingen http",
                "drosfeer landinname impact op biodiversiteit d",
                "ecologie - milieubeheer inhoud om de ",
                "unctioneren van een ecosysteem  het vak ecologie i",
                " ecosysteem  het vak ecologie is daarom opgedeeld",
                "er en verschillende ecosystemen  ecologisch functio",
                "illende ecosystemen  ecologisch functioneren  wat i",
                "functioneren  wat is ecologie biosfeer - hydrosfe",
                "ynamiek dynamiek in ecosystemen antropogene invloed",
                "ne invloeden op het milieu verstoringen in de "
            ],
            "[klima+t[^ ]*, milieu, [ ]ecolo[^ ]+": [
                "eer - atmosfeer het klimaat zon als energiebron",
                "gen in de atmosfeer klimaatverandering verstoring van de h",
                "ecologie - milieubeheer inhoud om de ",
                "ne invloeden op het milieu verstoringen in de ",
                " ecosysteem  het vak ecologie is daarom opgedee",
                "illende ecosystemen  ecologisch functioneren  w",
                "functioneren  wat is ecologie biosfeer - hydros"
            ],
            "[milieubeheer, [ ]ecolo[^ ]+, impact]": [
                "ecologie - milieubeheer inhoud om de effect",
                " ecosysteem  het vak ecologie is daarom opgedeeld",
                "illende ecosystemen  ecologisch functioneren  wat i",
                "functioneren  wat is ecologie biosfeer - hydrosfe",
                "drosfeer landinname impact op biodiversiteit d"
            ],
            "klimaatverandering": [
                "gen in de atmosfeer klimaatverandering verstoring van de h"
            ],
            "milieu[- ]?beheer": [
                "ecologie - milieubeheer inhoud om de effect"
            ],
            "milieubeheer": [
                "ecologie - milieubeheer inhoud om de effect"
            ]
        }
    },
    "JPW357: Milieutechnologie 2: bodem en lucht": {
        "nl": {
            "hernieuwbare energie": [
                "ve energiebronnen - hernieuwbare energiebronnen doelstelling"
            ],
            "bodemverontreiniging|verontreinigde grond": [
                "estrijdingsmethoden bodemverontreiniging  -voorkomen en oorz"
            ]
        }
    },
    "JPWD29: 4 Energie en Comfort 2": {
        "nl": {
            "energie[- ]?(?:ge|ver)bruik|(?:ge|ver)bruik van energie": [
                "comforteisen versus energieverbruik  - regelgeving  epb"
            ]
        }
    },
    "OAB07A: 5 Summer school sustainable management": {
        "en": {
            "sustainable management": [
                "5 summer school sustainable management inhoud the cases fo",
                "ional summer school sustainable management offers students a g",
                "ional summer school sustainable management should  take part i",
                "ional summer school sustainable management  take part in an ev",
                "ional summer school sustainable management are based on wiek s"
            ]
        }
    },
    "OAC04A: 5+6 Summer school": {
        "en": {
            "[sustainable solution, environment|[ ]ecolo[^ ]+]": [
                "s have to formulate sustainable solutions and advices for th",
                "imulate innovative  sustainable solutions  the participants ",
                "t domains  society  environment  economy  etc   and"
            ],
            "[sustainable solution, impact]": [
                "s have to formulate sustainable solutions and advices for th",
                "imulate innovative  sustainable solutions  the participants ",
                "  to understand the impact of sustainable mana"
            ],
            "sustainable management": [
                "n the summer school sustainable management  if so the student ",
                "  the summer school sustainable management focuses on non-form",
                "n the summer school sustainable management  if so the student ",
                "s the summer school sustainable management  the summer school ",
                "  the summer school sustainable management is a short intensiv",
                "s with education on sustainable management  the first edition ",
                "n the summer school sustainable management  you should partici",
                "stand the impact of sustainable management -          to incre",
                " the value added by sustainable management -          to disco",
                "pportunities within sustainable management -          to ackno",
                " and approaches for sustainable management to formulate innova"
            ]
        }
    },
    "OAK05A: Vakdidactiek 2.1": {
        "nl": {
            "milieuproble+m": [
                "nderwijs 8 4        milieuproblemen 9   ordenen van d"
            ],
            "(?:milieu|[ ]ecolo[^ ]+|ecosyst[^ ]+)proble+m": [
                "nderwijs 8 4        milieuproblemen 9   ordenen van d"
            ]
        }
    },
    "OAK21A: HAO Vakdidactiek 2.1": {
        "nl": {
            "milieuproble+m": [
                "nderwijs 8 4        milieuproblemen 9   ordenen van d"
            ],
            "(?:milieu|[ ]ecolo[^ ]+|ecosyst[^ ]+)proble+m": [
                "nderwijs 8 4        milieuproblemen 9   ordenen van d"
            ]
        }
    },
    "OAK35A: Schoolbeleid 3.2": {
        "nl": {
            "[duurzame ontwikkeling, milieu|[ ]ecolo[^ ]+]": [
                "eleid  scholen voor duurzame ontwikkeling   milieuzorg op sch",
                "zame ontwikkeling   milieuzorg op school  mos "
            ]
        }
    },
    "OAK50A: HAO Schoolbeleid 3.2": {
        "nl": {
            "[duurzame ontwikkeling, milieu|[ ]ecolo[^ ]+]": [
                "eleid  scholen voor duurzame ontwikkeling   milieuzorg op sch",
                "zame ontwikkeling   milieuzorg op school  mos "
            ]
        }
    },
    "OAK57A: Natuur 3": {
        "nl": {
            "[duurzame ontwikkeling, milieu|[ ]ecolo[^ ]+]": [
                "ratie met kinderen  duurzame ontwikkeling en milieuzorg   bas",
                "ame ontwikkeling en milieuzorg   basisprincipe"
            ]
        }
    },
    "OAK65A: HAO Natuur 3": {
        "nl": {
            "[duurzame ontwikkeling, milieu|[ ]ecolo[^ ]+]": [
                "oratie met kinderen duurzame ontwikkeling en milieuzorg   bas",
                "ame ontwikkeling en milieuzorg   basisprincipe"
            ]
        }
    },
    "OAK70A: Vakdidactiek 1.1": {
        "nl": {
            "[duurzame ontwikkeling, milieu|[ ]ecolo[^ ]+]": [
                "n de kleuterschool/ duurzame ontwikkeling/ educatie voor duur",
                "ling/ educatie voor duurzame ontwikkeling  b  levende natuur ",
                "ipes van natuur- en milieueducatie in de kleut"
            ],
            "milieueducatie": [
                "ipes van natuur- en milieueducatie in de kleuterschool"
            ]
        }
    },
    "OAK78A: HAO Vakdidactiek 1.1": {
        "nl": {
            "[duurzame ontwikkeling, milieu|[ ]ecolo[^ ]+]": [
                "n de kleuterschool/ duurzame ontwikkeling/ educatie voor duur",
                "ling/ educatie voor duurzame ontwikkeling b  levende natuur v",
                "ipes van natuur- en milieueducatie in de kleut"
            ],
            "milieueducatie": [
                "ipes van natuur- en milieueducatie in de kleuterschool"
            ]
        }
    },
    "OAL51A: Natuurbeleving: kinderen en natuur in de kijker 3": {
        "nl": {
            "[duurzame ontwikkeling, milieu|[ ]ecolo[^ ]+]": [
                "ratie met kinderen  duurzame ontwikkeling en milieuzorg   bas",
                "sie rond natuur- en milieueducatie  relevante ",
                "ame ontwikkeling en milieuzorg   basisprincipe"
            ],
            "milieueducatie": [
                "sie rond natuur- en milieueducatie  relevante literatu"
            ]
        }
    },
    "OAL58A: Schoolbeleid 3.2": {
        "nl": {
            "[duurzame ontwikkeling, milieu|[ ]ecolo[^ ]+]": [
                "id en educatie voor duurzame ontwikkeling binnen  schoolbelei",
                "nen  schoolbeleid   milieuzorg op school  mos "
            ]
        }
    },
    "OAL68A: HAO Schoolbeleid 3.2": {
        "nl": {
            "[duurzame ontwikkeling, milieu|[ ]ecolo[^ ]+]": [
                "id en educatie voor duurzame ontwikkeling binnen  schoolbelei",
                "leid   scholen voor duurzame ontwikkeling  milieuzorg op scho",
                "rzame ontwikkeling  milieuzorg op school  mos "
            ]
        }
    },
    "OAL73A: HAO Natuurbeleving: kinderen en natuur in de kijker 3": {
        "nl": {
            "[duurzame ontwikkeling, milieu|[ ]ecolo[^ ]+]": [
                "ratie met kinderen  duurzame ontwikkeling en milieuzorg   bas",
                "sie rond natuur- en milieueducatie  relevante ",
                "ame ontwikkeling en milieuzorg   basisprincipe"
            ],
            "milieueducatie": [
                "sie rond natuur- en milieueducatie  relevante literatu"
            ]
        }
    },
    "OAR01C: Korte mobiliteit": {
        "nl": {
            "[duurza+m(?:heid)?, mobiliteit]": [
                "e mobiliteit is een duurzame samenwerking met d",
                "korte mobiliteit inhoud deze leeract",
                " wordt er een korte mobiliteit ingericht voor de g",
                "ader van deze korte mobiliteit is een duurzame sam"
            ]
        }
    },
    "OAR01G: 3 Constructie van gebouwen 3": {
        "nl": {
            "duurzaam bouwen": [
                "ng facultatief  #   duurzaam bouwen levenscyclusanalyse"
            ],
            "levenscyclusanalyse": [
                "#   duurzaam bouwen levenscyclusanalyse  inhoud grafische i"
            ]
        }
    },
    "OBK21A: E to the power of three: Teaching in Europe - Europe in teaching": {
        "nl": {
            "duurzame ontwikkelingsdoel(?:en|stelling)?": [
                "eit en educatie  17 duurzame ontwikkelingsdoelen  verenigde naties  "
            ]
        }
    },
    "OGC00D: Milieuwetgeving": {
        "nl": {
            "milieu[- ]?wet": [
                "milieuwetgeving inhoud 1 mili",
                "ling van de vlaamse milieuwetgeving 3 1 sectoraal",
                "odernisering van de milieuwetgeving 3 3 meest rec"
            ]
        }
    },
    "OGC00L: Milieuzorg": {
        "nl": {
            "bodemverontreiniging|verontreinigde grond": [
                "estrijdingsmethoden bodemverontreiniging + bodemsaneringstec"
            ]
        }
    },
    "OGC00N: Bedrijfsinterne milieuzorg": {
        "nl": {
            "milieubeleid": [
                "ms  norm 4 1  3 3 7 milieubeleid  norm 4 2  3 3 8 pl"
            ],
            "milieuverantwoordelijk": [
                "ilieucoordinator vs milieuverantwoordelijke en milieudeskundig"
            ]
        }
    },
    "OGC00Y: Biologisch milieuonderzoek": {
        "nl": {
            "[bio(?:diversiteit|sfeer), ecosyst[^ ]+]": [
                "le rol van bomen en biodiversiteit in de klimaatopwarm",
                " componenten in ons ecosysteem zijn sterk verweven",
                "orgt ervoor dat een ecosysteem in balans is en zel",
                "t doorheen het hele ecosysteem zijn gevolgen zal h",
                "or voedselketens en ecosystemen belang als indicato"
            ],
            "[bio(?:diversiteit|sfeer), gevolg, milieu|[ ]ecolo[^ ]+|ecosyst[^ ]+]": [
                "le rol van bomen en biodiversiteit in de klimaatopwarm",
                "ele ecosysteem zijn gevolgen zal hebben  door ",
                "biologisch milieuonderzoek inhoud de ",
                " componenten in ons ecosysteem zijn sterk verweven",
                "orgt ervoor dat een ecosysteem in balans is en zel",
                "t doorheen het hele ecosysteem zijn gevolgen zal h",
                "e kwaliteit van het milieu en eventuele onbala",
                "n we het biologisch milieuonderzoek  1  biolog",
                "or voedselketens en ecosystemen belang als indicato",
                "ader van biologisch milieuonderzoek deze oefen",
                "estaande biologisch milieuonderzoek dat onder ",
                "an het laboratorium milieutoxicologie  ghentox"
            ],
            "[ecosyst[^ ]+, pollutie]": [
                " componenten in ons ecosysteem zijn sterk verweven",
                "orgt ervoor dat een ecosysteem in balans is en zel",
                "t doorheen het hele ecosysteem zijn gevolgen zal h",
                "or voedselketens en ecosystemen belang als indicato",
                " densiteitsmetingen pollutie indices  saprobie s"
            ],
            "ecotoxicologie": [
                "eren  mmif   thema  ecotoxicologie en bioassay labo 7 "
            ]
        }
    },
    "OGE01G: Warmtetechniek HVAC": {
        "nl": {
            "fossiele brandstof": [
                "uwen verwarming met fossiele brandstoffen gas stookolie ve"
            ]
        }
    },
    "OGE01L: Toegepaste wetenschappen": {
        "nl": {
            "windenergie": [
                "n klimaat  energie  windenergie  getijdenenergie   "
            ]
        }
    },
    "OGF00J: Facilitair beleid 1": {
        "nl": {
            "milieu[- ]?vriendelijk": [
                " een ecologische en milieuvriendelijke  werk omgeving dlr"
            ]
        }
    },
    "OGF00P: Technologie & Innovatie 1": {
        "nl": {
            "milieu[- ]?vriendelijk": [
                " een ecologische en milieuvriendelijke  werk omgeving dlr"
            ]
        }
    },
    "OGF00Q: Milieu & Ecologie 1": {
        "nl": {
            "[bio(?:diversiteit|sfeer), [ ]ecolo[^ ]+]": [
                "wat is ecologie  de biosfeer het klimaat zon als",
                "milieu & ecologie 1 inhoud deel 1   i",
                "l 2 inleiding tot de ecologie en milieuproblemati",
                "wat is milieuleer of ecologie  aanverwante wetens",
                "etenschappen  deel 3 ecologie wat is ecologie  de",
                "el 3 ecologie wat is ecologie  de biosfeer het kl",
                "r beheer bij aan een ecologische en milieuvriendelij"
            ],
            "[bio(?:diversiteit|sfeer), ecosyst[^ ]+]": [
                "wat is ecologie  de biosfeer het klimaat zon als",
                "iek dynamiek in het ecosysteem antropogene invloed"
            ],
            "[bio(?:diversiteit|sfeer), proble+m, milieu|[ ]ecolo[^ ]+|ecosyst[^ ]+]": [
                "wat is ecologie  de biosfeer het klimaat zon als",
                "e ecologie en milieuproblematiek inleiding ontw",
                " ontstaan tgv milieuproblemen  the great smog  ",
                "milieu & ecologie 1 inhoud",
                "milieu & ecologie 1 inhoud deel 1   i",
                "l 2 inleiding tot de ecologie en milieuproblemati",
                " tot de ecologie en milieuproblematiek inleidi",
                "ontwikkeling van de milieuwetenschappen  -rech",
                "-recht obv groeiend milieubewustzijn ontstaan ",
                "stzijn ontstaan tgv milieuproblemen  the great",
                "urzame ontwikkeling milieuleer wat is milieu  ",
                "g milieuleer wat is milieu  wat is natuur  fil",
                "is de definitie van milieu in onze samenleving",
                "samenleving  wat is milieuleer of ecologie  aa",
                "wat is milieuleer of ecologie  aanverwante wetens",
                "nte wetenschappen - milieuwetenschappen  deel ",
                "etenschappen  deel 3 ecologie wat is ecologie  de",
                "el 3 ecologie wat is ecologie  de biosfeer het kl",
                "iek dynamiek in het ecosysteem antropogene invloed",
                "ne invloeden op het milieu  deel 4 duurzame fa",
                "an ik gebruiken  de milieuwetgeving duurzaamhe",
                "e  cradle-to-cradle milieumanagementsystemen m",
                "umanagementsystemen milieu-aspectenmatrix mili",
                "lieu-aspectenmatrix milieurisico-analyse iso-n",
                "ere normen  breeam  milieukeuren  -certificate",
                "r beheer bij aan een ecologische en milieuvriendelij",
                " een ecologische en milieuvriendelijke  werk o"
            ],
            "[duurza+m(?:heid)?, mobiliteit]": [
                " introductie tot de duurzaamheid introductie basiske",
                "ritisch denken rond duurzaamheid  deel 2 inleiding t",
                "ure  - principe van duurzame ontwikkeling milie",
                " het milieu  deel 4 duurzame facilitaire oploss",
                " de milieuwetgeving duurzaamheid vertrekkende vanuit",
                "tbeheer catering en duurzame voeding schoonmaak",
                "ent draagt door een duurzaam facilitair beheer b",
                "s-office    aankoop mobiliteit en fleetbeheer cate"
            ],
            "[duurzame ontwikkeling, milieu, [ ]ecolo[^ ]+|ecosyst[^ ]+]": [
                "ure  - principe van duurzame ontwikkeling milieuleer wat is m",
                "milieu & ecologie 1 inhoud",
                " tot de ecologie en milieuproblematiek inleidi",
                "ontwikkeling van de milieuwetenschappen  -rech",
                "-recht obv groeiend milieubewustzijn ontstaan ",
                "stzijn ontstaan tgv milieuproblemen  the great",
                "urzame ontwikkeling milieuleer wat is milieu  ",
                "g milieuleer wat is milieu  wat is natuur  fil",
                "is de definitie van milieu in onze samenleving",
                "samenleving  wat is milieuleer of ecologie  aa",
                "nte wetenschappen - milieuwetenschappen  deel ",
                "ne invloeden op het milieu  deel 4 duurzame fa",
                "an ik gebruiken  de milieuwetgeving duurzaamhe",
                "e  cradle-to-cradle milieumanagementsystemen m",
                "umanagementsystemen milieu-aspectenmatrix mili",
                "lieu-aspectenmatrix milieurisico-analyse iso-n",
                "ere normen  breeam  milieukeuren  -certificate",
                " een ecologische en milieuvriendelijke  werk o",
                "milieu & ecologie 1 inhoud deel 1   i",
                "l 2 inleiding tot de ecologie en milieuproblemati",
                "wat is milieuleer of ecologie  aanverwante wetens",
                "etenschappen  deel 3 ecologie wat is ecologie  de",
                "el 3 ecologie wat is ecologie  de biosfeer het kl",
                "iek dynamiek in het ecosysteem antropogene invloed",
                "r beheer bij aan een ecologische en milieuvriendelij"
            ],
            "[duurzame ontwikkeling, milieu-?proble+m]": [
                "ure  - principe van duurzame ontwikkeling milieuleer wat is m",
                " tot de ecologie en milieuproblematiek inleiding ontw",
                "stzijn ontstaan tgv milieuproblemen  the great smog  "
            ],
            "[duurzame ontwikkeling, milieu-?wet]": [
                "ure  - principe van duurzame ontwikkeling milieuleer wat is m",
                "ontwikkeling van de milieuwetenschappen  -recht o",
                "nte wetenschappen - milieuwetenschappen  deel 3 e",
                "an ik gebruiken  de milieuwetgeving duurzaamheid "
            ],
            "[duurzame ontwikkeling, milieu|[ ]ecolo[^ ]+]": [
                "ure  - principe van duurzame ontwikkeling milieuleer wat is m",
                "milieu & ecologie 1 inhoud",
                "milieu & ecologie 1 inhoud deel 1   i",
                "l 2 inleiding tot de ecologie en milieuproblemati",
                " tot de ecologie en milieuproblematiek inleidi",
                "ontwikkeling van de milieuwetenschappen  -rech",
                "-recht obv groeiend milieubewustzijn ontstaan ",
                "stzijn ontstaan tgv milieuproblemen  the great",
                "urzame ontwikkeling milieuleer wat is milieu  ",
                "g milieuleer wat is milieu  wat is natuur  fil",
                "is de definitie van milieu in onze samenleving",
                "samenleving  wat is milieuleer of ecologie  aa",
                "wat is milieuleer of ecologie  aanverwante wetens",
                "nte wetenschappen - milieuwetenschappen  deel ",
                "etenschappen  deel 3 ecologie wat is ecologie  de",
                "el 3 ecologie wat is ecologie  de biosfeer het kl",
                "ne invloeden op het milieu  deel 4 duurzame fa",
                "an ik gebruiken  de milieuwetgeving duurzaamhe",
                "e  cradle-to-cradle milieumanagementsystemen m",
                "umanagementsystemen milieu-aspectenmatrix mili",
                "lieu-aspectenmatrix milieurisico-analyse iso-n",
                "ere normen  breeam  milieukeuren  -certificate",
                "r beheer bij aan een ecologische en milieuvriendelij",
                " een ecologische en milieuvriendelijke  werk o"
            ],
            "[[ ]ecolo[^ ]+, duurzaamheid]": [
                "milieu & ecologie 1 inhoud deel 1   i",
                "l 2 inleiding tot de ecologie en milieuproblemati",
                "wat is milieuleer of ecologie  aanverwante wetens",
                "etenschappen  deel 3 ecologie wat is ecologie  de",
                "el 3 ecologie wat is ecologie  de biosfeer het kl",
                "r beheer bij aan een ecologische en milieuvriendelij",
                " introductie tot de duurzaamheid introductie basiske",
                "ritisch denken rond duurzaamheid  deel 2 inleiding t",
                " de milieuwetgeving duurzaamheid vertrekkende vanuit"
            ],
            "[klima+t[^ ]*, milieu, [ ]ecolo[^ ]+": [
                "ie  de biosfeer het klimaat zon als energiebron",
                "milieu & ecologie 1 inhoud",
                " tot de ecologie en milieuproblematiek inleidi",
                "ontwikkeling van de milieuwetenschappen  -rech",
                "-recht obv groeiend milieubewustzijn ontstaan ",
                "stzijn ontstaan tgv milieuproblemen  the great",
                "urzame ontwikkeling milieuleer wat is milieu  ",
                "g milieuleer wat is milieu  wat is natuur  fil",
                "is de definitie van milieu in onze samenleving",
                "samenleving  wat is milieuleer of ecologie  aa",
                "nte wetenschappen - milieuwetenschappen  deel ",
                "ne invloeden op het milieu  deel 4 duurzame fa",
                "an ik gebruiken  de milieuwetgeving duurzaamhe",
                "e  cradle-to-cradle milieumanagementsystemen m",
                "umanagementsystemen milieu-aspectenmatrix mili",
                "lieu-aspectenmatrix milieurisico-analyse iso-n",
                "ere normen  breeam  milieukeuren  -certificate",
                " een ecologische en milieuvriendelijke  werk o",
                "milieu & ecologie 1 inhoud deel 1  ",
                "l 2 inleiding tot de ecologie en milieuproblema",
                "wat is milieuleer of ecologie  aanverwante wete",
                "etenschappen  deel 3 ecologie wat is ecologie  ",
                "el 3 ecologie wat is ecologie  de biosfeer het ",
                "r beheer bij aan een ecologische en milieuvrien"
            ],
            "circulaire economie": [
                "e economie naar een circulaire economie  cradle-to-cradle m"
            ],
            "milieu[- ]?management": [
                "e  cradle-to-cradle milieumanagementsystemen milieu-aspe"
            ],
            "milieu[- ]?vriendelijk": [
                " een ecologische en milieuvriendelijke  werk omgevin"
            ],
            "milieu[- ]?wet": [
                "ontwikkeling van de milieuwetenschappen  -recht o",
                "nte wetenschappen - milieuwetenschappen  deel 3 e",
                "an ik gebruiken  de milieuwetgeving duurzaamheid "
            ],
            "milieuproble+m": [
                " tot de ecologie en milieuproblematiek inleiding ontw",
                "stzijn ontstaan tgv milieuproblemen  the great smog  "
            ],
            "(?:milieu|[ ]ecolo[^ ]+|ecosyst[^ ]+)proble+m": [
                " tot de ecologie en milieuproblematiek inleiding ontw",
                "stzijn ontstaan tgv milieuproblemen  the great smog  "
            ]
        }
    },
    "OGF00R: Duurzame huisvesting 1": {
        "nl": {
            "[klima+t[^ ]*, milieu, [ ]ecolo[^ ]+": [
                "g gezondheid  binnenklimaat  legionellabeheersi",
                " een ecologische en milieuvriendelijke  werk o",
                "r beheer bij aan een ecologische en milieuvrien"
            ],
            "milieu[- ]?vriendelijk": [
                " een ecologische en milieuvriendelijke  werk omgeving zor"
            ]
        }
    },
    "OGF00V: Milieu & Ecologie 2": {
        "nl": {
            "milieu[- ]?vriendelijk": [
                " een ecologische en milieuvriendelijke  werk omgeving  - "
            ],
            "milieuregelgeving": [
                "& ecologie 2 inhoud milieuregelgeving/omgevingswetgeving "
            ]
        }
    },
    "OGF00W: Hospitality 3": {
        "nl": {
            "milieu[- ]?vriendelijk": [
                " een ecologische en milieuvriendelijke  werk omgeving  de"
            ]
        }
    },
    "OGF00X: Health, Safety & Security 1": {
        "nl": {
            "milieu[- ]?vriendelijk": [
                " een ecologische en milieuvriendelijke  werk omgeving  de"
            ]
        }
    },
    "OGP00R: Toegepaste mechanica 3": {
        "nl": {
            "hernieuwbare energie": [
                "n eigenschappen van hernieuwbare energietechnieken kunnen om"
            ]
        }
    },
    "OGP01C: Toegepaste mechanica 3 vervolgtraject": {
        "nl": {
            "hernieuwbare energie": [
                "n eigenschappen van hernieuwbare energietechnieken kunnen om"
            ]
        }
    },
    "OGT33A: Skills for the future": {
        "nl": {
            "duurzame ontwikkelingsdoel(?:en|stelling)?": [
                "lk project staan de duurzame ontwikkelingsdoelstellingen of sustainable de"
            ]
        }
    },
    "OKK00H: Veiligheid, Milieu en Kwaliteit": {
        "nl": {
            "energie[- ]?(?:ge|ver)bruik|(?:ge|ver)bruik van energie": [
                "e sorteren en grote energieverbruikers op de bedrijfsvl"
            ]
        }
    },
    "OKW00I: 2 Uitvoeringstechnieken Gebouwen 1": {
        "nl": {
            "duurzaam bouwen": [
                "basisbeginselen van duurzaam bouwen en van de bouwfysic"
            ]
        }
    },
    "OKW00J: 2 Uitvoeringstechnieken Infrastructuur 1": {
        "nl": {
            "duurzaam bouwen": [
                "basisbeginselen van duurzaam bouwen krijgen meer tastba"
            ]
        }
    },
    "OKW00P: 3 Uitvoeringstechnieken Gebouwen 2": {
        "nl": {
            "duurzaam bouwen": [
                "basisbeginselen van duurzaam bouwen en van de bouwfysic"
            ],
            "energie[- ]?(?:ge|ver)bruik|(?:ge|ver)bruik van energie": [
                "duurzaamheid en het energieverbruik van een woning  de "
            ],
            "hernieuwbare energie": [
                " bijv  klassieke en hernieuwbare energie- of warmtebronnen s"
            ]
        }
    },
    "OKW00R: 3 Uitvoeringstechnieken Infrastructuur 2": {
        "nl": {
            "duurzaam bouwen": [
                "basisbeginselen van duurzaam bouwen zijn geintegreerd e"
            ]
        }
    },
    "OKW01A: 1 Verkenning Werkveld": {
        "nl": {
            "duurzaam bouwen": [
                " m  bouwfysica  van duurzaam bouwen en van de goede bou"
            ]
        }
    },
    "OO3144: Aardrijkskunde: Weer en klimaat": {
        "nl": {
            "klimaatverandering": [
                " 1 waarnemingen van klimaatverandering 5 2 factoren die va",
                " invloed zijn op de klimaatverandering 5 3 toekomstige ris"
            ],
            "opwarming van de aarde": [
                "4 2 de el nino 5 de opwarming van de aarde 5 1 waarnemingen va"
            ]
        }
    },
    "OO3150: Economie: Algemene economie 2.2": {
        "nl": {
            "[duurzame ontwikkeling, milieu|[ ]ecolo[^ ]+]": [
                "r  groei  milieu en duurzame ontwikkeling sociaal recht doels",
                "conjunctuur  groei  milieu en duurzame ontwikk"
            ]
        }
    },
    "OWA00S: Agro- en Biotechnologie voor de 21e eeuw": {
        "nl": {
            "[duurzame ontwikkeling, milieu, [ ]ecolo[^ ]+|ecosyst[^ ]+]": [
                "in zijn ecosysteem  duurzame ontwikkeling  duurzaam onderneme",
                "rende maatschappij  milieu en klimaat  voedsel",
                "jn  de mens in zijn ecosysteem  duurzame ontwikkel"
            ],
            "[duurzame ontwikkeling, milieu|[ ]ecolo[^ ]+]": [
                "in zijn ecosysteem  duurzame ontwikkeling  duurzaam onderneme",
                "rende maatschappij  milieu en klimaat  voedsel"
            ]
        }
    },
    "OWA01R: Plantaardige productie": {
        "nl": {
            "[bio(?:diversiteit|sfeer), [ ]ecolo[^ ]+]": [
                "urdoelen samengaan  biodiversiteit en bodembeheer spel",
                "plantenvoeding in de ecologische teeltwijze worden t"
            ],
            "[[ ]ecolo[^ ]+, klima+t[^ ]*, landbouw]": [
                "plantenvoeding in de ecologische teeltwijze worden t",
                "aan het veranderend klimaat  daarom worden nieu",
                "d zal staan  inhoud landbouw zorgt voor ons dage",
                "regelmatig strijden landbouw en natuur om hun gr",
                "raag naar voldoende landbouwgrond neemt toe door",
                "kkeling en duurzame landbouw  kunnen agrarische ",
                "asrotatie  kringlooplandbouw maken deel uit van ",
                "n natuur inclusieve landbouw  ook plantenveredel",
                "basis voor duurzame landbouw  in dit onderdeel i"
            ],
            "[klima+t[^ ]*, milieu, [ ]ecolo[^ ]+": [
                "aan het veranderend klimaat  daarom worden nieu",
                "ap  de natuur en de milieukwaliteit  regelmati",
                "plantenvoeding in de ecologische teeltwijze wor"
            ],
            "duurzame landbouw": [
                "tuurontwikkeling en duurzame landbouw  kunnen agrarische ",
                " mee een basis voor duurzame landbouw  in dit onderdeel i"
            ]
        }
    }
}