[
 {
  "id":"SH505",
  "name":"Conna\u00eetre, actualiser et int\u00e9grer un savoir disciplinaire en sciences sociales (gouvernance mondiale)",
  "year":"2022-2023",
  "languages":[
   "fr"
  ],
  "teachers":[
   "Navez V\u00e9ronique"
  ],
  "url":"https:\/\/www.galileonet.be\/extranet\/index.php?controller=DescriptifsDeCours&action=getViewGestionUE&id=&cue=U0g1MDU=&ec=2",
  "cycles":[
   "bac"
  ],
  "fields":[
   "Pedagogy"
  ],
  "themes":[
   "resources",
   "sustainability"
  ],
  "dedicated":0
 },
 {
  "id":"SH508",
  "name":"Conna\u00eetre et appliquer un savoir disciplinaire en g\u00e9ographie",
  "year":"2022-2023",
  "languages":[
   "fr"
  ],
  "teachers":[
   "Carnat Gauthier"
  ],
  "url":"https:\/\/www.galileonet.be\/extranet\/index.php?controller=DescriptifsDeCours&action=getViewGestionUE&id=&cue=U0g1MDg=&ec=2",
  "cycles":[
   "bac"
  ],
  "fields":[
   "Pedagogy"
  ],
  "themes":[
   "energy"
  ],
  "dedicated":0
 },
 {
  "id":"SN404",
  "name":"Physique et didactique",
  "year":"2022-2023",
  "languages":[
   "fr"
  ],
  "teachers":[
   "Payen Florian"
  ],
  "url":"https:\/\/www.galileonet.be\/extranet\/index.php?controller=DescriptifsDeCours&action=getViewGestionUE&id=&cue=U040MDQ=&ec=2",
  "cycles":[
   "bac"
  ],
  "fields":[
   "Pedagogy"
  ],
  "themes":[
   "climate"
  ],
  "dedicated":0
 }
]